MANIFEST.in
README.md
setup.py
redash_dynamic_query/__init__.py
redash_dynamic_query.egg-info/PKG-INFO
redash_dynamic_query.egg-info/SOURCES.txt
redash_dynamic_query.egg-info/dependency_links.txt
redash_dynamic_query.egg-info/entry_points.txt
redash_dynamic_query.egg-info/requires.txt
redash_dynamic_query.egg-info/top_level.txt
redash_dynamic_query/cli/__init__.py
redash_dynamic_query/cli/main.py