Metadata-Version: 1.1
Name: redash-dynamic-query
Version: 1.0.4
Summary: Redash Dynamic Query
Home-page: https://github.com/toritori0318/redash-dynamic-query
Author: toritori0318
Author-email: toritori0318@gmail.com
License: MIT
Keywords: redash
Platform: UNKNOWN
Classifier: Development Status :: 3 - Alpha
Classifier: Intended Audience :: Developers
Classifier: Topic :: Software Development :: Build Tools
Classifier: License :: OSI Approved :: MIT License
Classifier: Programming Language :: Python :: 2
Classifier: Programming Language :: Python :: 2.6
Classifier: Programming Language :: Python :: 2.7
Classifier: Programming Language :: Python :: 3
Classifier: Programming Language :: Python :: 3.3
Classifier: Programming Language :: Python :: 3.4
Classifier: Programming Language :: Python :: 3.5
